smap_window/__init__.py
smap_window/arguments.py
smap_window/haplotype_window.py
smap_window/version.py
smap_haplotype_window-1.8.1.dist-info/LICENSE
smap_haplotype_window-1.8.1.dist-info/METADATA
smap_haplotype_window-1.8.1.dist-info/WHEEL
smap_haplotype_window-1.8.1.dist-info/entry_points.txt
smap_haplotype_window-1.8.1.dist-info/top_level.txt
smap_haplotype_window-1.8.1.dist-info/RECORD
