Metadata-Version: 2.1
Name: smap-haplotype-window
Version: 1.8.1
Summary: Haplotype-window is a SMAP component that performs haplotyping between pairs of borders defined in a reference genome.
Home-page: https://ngs-smap.readthedocs.io/en/latest/
Author-email: dries.schaumont@ilvo.vlaanderen.be
License: Attribution-NonCommercial-ShareAlike 4.0 International
Classifier: Programming Language :: Python :: 3
Requires-Python: >=3.8.1
License-File: LICENSE
Requires-Dist: ngs-smap (<=4.7,>=4.5)
Requires-Dist: cutadapt
Provides-Extra: docs
Requires-Dist: sphinx (~=4.4.0) ; extra == 'docs'
Requires-Dist: sphinx-rtd-theme (~=1.0.0) ; extra == 'docs'
Requires-Dist: sphinx-tabs (~=3.2.0) ; extra == 'docs'
Requires-Dist: sphinx-subprojecttoctree (~=0.3.1) ; extra == 'docs'
